smart_exceptions/__init__.py
smart_exceptions/run_env.py
smart_exceptions/utils.py
smart_exceptions/backends/__init__.py
smart_exceptions/backends/anthropic.py
smart_exceptions/backends/base.py
smart_exceptions/backends/groq.py
smart_exceptions/backends/openai.py
smart_exceptions-0.1.0.dist-info/LICENSE.txt
smart_exceptions-0.1.0.dist-info/METADATA
smart_exceptions-0.1.0.dist-info/WHEEL
smart_exceptions-0.1.0.dist-info/top_level.txt
smart_exceptions-0.1.0.dist-info/RECORD
