Metadata-Version: 2.1
Name: smart-exceptions
Version: 0.1.0
License-File: LICENSE.txt
Requires-Dist: openai ==1.12.0
Requires-Dist: tiktoken ==0.7.0
Requires-Dist: anthropic ==0.20.0
Requires-Dist: groq ==0.5.0
Requires-Dist: rich ~=13.7
Requires-Dist: importlib-metadata ; python_version > "3.10"
